{
    "browsers": [
        {
            "filename": "AIMP.zip",
            "url": "https://github.com/Snaky1a/xp-apps/releases/download/2023_10_11_17_52/AIMP.zip",
            "name": "app"
        },
        {
            "filename": "test.zip",
            "url": "https://github.com/Snaky1a/xp-apps/releases/download/2023_10_11_17_52/AIMP.zip",
            "name": "app2"
        }
    ],
    "category2": [
        {
            "app3": {
                "filename": "AIMP.zip",
                "url": "https://github.com/Snaky1a/xp-apps/releases/download/2023_10_11_17_52/AIMP.zip"
            }
        }
    ]
}
